powerfactory_tools/__init__.py
powerfactory_tools/__version__.py
powerfactory_tools/powerfactory_error_codes.py
powerfactory_tools/str_constants.py
powerfactory_tools/utils/__init__.py
powerfactory_tools/utils/io.py
powerfactory_tools/versions/pf2022/__init__.py
powerfactory_tools/versions/pf2022/constants.py
powerfactory_tools/versions/pf2022/data.py
powerfactory_tools/versions/pf2022/interface.py
powerfactory_tools/versions/pf2022/quantities.py
powerfactory_tools/versions/pf2022/types.py
powerfactory_tools/versions/pf2022/exporter/__init__.py
powerfactory_tools/versions/pf2022/exporter/exporter.py
powerfactory_tools/versions/pf2022/exporter/load_power.py
powerfactory_tools/versions/pf2024/__init__.py
powerfactory_tools/versions/pf2024/constants.py
powerfactory_tools/versions/pf2024/data.py
powerfactory_tools/versions/pf2024/interface.py
powerfactory_tools/versions/pf2024/quantities.py
powerfactory_tools/versions/pf2024/types.py
powerfactory_tools/versions/pf2024/exporter/__init__.py
powerfactory_tools/versions/pf2024/exporter/exporter.py
powerfactory_tools/versions/pf2024/exporter/load_power.py
ieeh_powerfactory_tools-3.2.2.dist-info/METADATA
ieeh_powerfactory_tools-3.2.2.dist-info/WHEEL
ieeh_powerfactory_tools-3.2.2.dist-info/licenses/AUTHORS.md
ieeh_powerfactory_tools-3.2.2.dist-info/licenses/LICENSE
ieeh_powerfactory_tools-3.2.2.dist-info/RECORD
