Metadata-Version: 2.4
Name: ieeh-powerfactory-tools
Version: 3.2.2
Summary: A toolbox for Python based control of DIgSILENT PowerFactory
Project-URL: Source, https://github.com/ieeh-tu-dresden/powerfactory-tools
Author-email: Sasan Jacob Rasti <sasan_jacob.rasti@tu-dresden.de>, Sebastian Krahmer <sebastian.krahmer@tu-dresden.de>, Laura Fiedler <laura.fiedler@tu-dresden.de>, Maximilian Schmidt <maximilian.schmidt@tu-dresden.de>
License: BSD 3-Clause License
License-File: AUTHORS.md
License-File: LICENSE
Requires-Python: <3.13,>=3.10
Requires-Dist: ieeh-power-system-data-model>=2.3.3
Requires-Dist: loguru>=0.7.3
Requires-Dist: pydantic>=2.10.6
Provides-Extra: io-pandas
Requires-Dist: pandas; extra == 'io-pandas'
Requires-Dist: pyarrow; extra == 'io-pandas'
Provides-Extra: io-polars
Requires-Dist: polars; extra == 'io-polars'
Requires-Dist: pyarrow; extra == 'io-polars'
